image_sitemap/__init__.py
image_sitemap/__version__.py
image_sitemap/images_crawler.py
image_sitemap/links_crawler.py
image_sitemap/main.py
image_sitemap/instruments/__init__.py
image_sitemap/instruments/config.py
image_sitemap/instruments/file.py
image_sitemap/instruments/templates.py
image_sitemap/instruments/web.py
image_sitemap-1.0.6.dist-info/licenses/LICENSE
image_sitemap-1.0.6.dist-info/METADATA
image_sitemap-1.0.6.dist-info/WHEEL
image_sitemap-1.0.6.dist-info/top_level.txt
image_sitemap-1.0.6.dist-info/RECORD
