Metadata-Version: 2.4
Name: image-sitemap
Version: 1.0.6
Summary: Library to generate XML sitemaps for websites and images. Boost SEO by indexing image URLs for better visibility on search engines.
Author-email: AndreiDrang <python-captcha@pm.me>
License-Expression: MIT
Project-URL: Homepage, https://github.com/AndreiDrang/image_sitemap
Project-URL: Documentation, https://github.com/AndreiDrang/image_sitemap
Project-URL: Repository, https://github.com/AndreiDrang/image_sitemap
Project-URL: Issues, https://github.com/AndreiDrang/image_sitemap/issues
Project-URL: Changelog, https://github.com/AndreiDrang/image_sitemap/releases
Keywords: sitemap generator,image sitemap,XML sitemap,SEO optimization,Python SEO tools,website indexing,search engine visibility,image indexing,web crawler
Classifier: Development Status :: 5 - Production/Stable
Classifier: Programming Language :: Python
Classifier: Programming Language :: Python :: 3
Classifier: Programming Language :: Python :: 3 :: Only
Classifier: Programming Language :: Python :: 3.12
Classifier: Programming Language :: Python :: 3.13
Classifier: Framework :: AsyncIO
Classifier: Operating System :: Unix
Classifier: Operating System :: Microsoft :: Windows
Classifier: Operating System :: MacOS
Requires-Python: >=3.12
License-File: LICENSE
Requires-Dist: aiohttp==3.*
Requires-Dist: beautifulsoup4==4.*
Dynamic: license-file
